myimg/__init__.py
myimg/api.py
myimg/objects.py
myimg/plots.py
myimg/settings.py
myimg/apps/__init__.py
myimg/apps/fft.py
myimg/apps/profiles.py
myimg/apps/simuParticles.py
myimg/apps/velox.py
myimg/apps/iLabels/__init__.py
myimg/apps/iLabels/classPeaks.py
myimg/apps/iLabels/classifiers.py
myimg/apps/iLabels/detectors.py
myimg/apps/iLabels/features.py
myimg/apps/iLabels/roi.py
myimg/utils/__init__.py
myimg/utils/caption.py
myimg/utils/iplot.py
myimg/utils/label.py
myimg/utils/scalebar.py
myimg-0.4.1.dist-info/licenses/LICENCE
myimg-0.4.1.dist-info/METADATA
myimg-0.4.1.dist-info/WHEEL
myimg-0.4.1.dist-info/top_level.txt
myimg-0.4.1.dist-info/RECORD
